{
  "name": "Franklin Nash",
  "age": 64,
  "address": {
    "street": "Zowjuh Court",
    "city": "Viffojlu",
    "state": "WI",
    "zip": "82428"
  },
  "contact": {
    "phone": "(821) 287-9020",
    "servicePhone": "800995895"
  },
  "birthday": "1976-12-27T05:25:11.306Z",
  "ip": "85.36.158.213",
  "foo": "bar",
  "profile": {
    "about": "Wiv uzkevizo wevih dikaheco nurow dized fusgoan ikece wotnahde vitoew omlamzim fepedlo kurodivu sozanaku. Fuwri dicku ago monu vulrun rajiez bafihe gamses dew ani ne bakugud gok sidbocam az ef. Uc vi get burwivir ned ejuke owat ducpeh vociv idu ruhsi uzukobgiz evaot cevlantob baleji jom. Uzwun ama itcuho madiz sa bere ri fihulucu vuccab pacadi ir kuesmo sob. Reohaz gidet nu jotagwo koh ji caracza pofobiv dusninor unucozu upu iguwamru ujuunowi wiguvvas enoav bak pazru ugu. Bemeh pafug kazule ri fubwagap dez tah mehfe itnum gesu raeg esage tu ohralij pubele caizlu se kirtag. Ro hezravjun sab runra sudirep igo cuwucbig juknimov lothud gafpes uwodo noczim piczubpa gepra zucurhum gim ejohubne.",
    "bio": "Pobus gakjuneg gucopda zilobjuh igvi etataw abnuj ca kahpasav zom kipaf zav vunmurteb guhkov. Wa ve capkawfa vufid heepnep jukek ri ahomiho elnirwuj no bezah ezisa hordahfeb zih fohseju mesar ko. Jececafa sugibur buenuulo rej ki juzho wezatkem fivvube lejhe vudke buj mo lelmuvzuk. Ova ciuvow bu egabok iha rohjid so fe oztop cu zac nil. Esotuase inorap ic to powcetar jumtacruh ru wikpu kiwehaduw usur etgi law ufzo lo holcuwid ipkajig ze oca."
  },
  "apiKey": "23c8f39e1bae3f4fa1a244ceaf8488ad9479989bd0e97d997fcca4ca0b2aa3e9",
  "currency": {
    "code": "GHS",
    "name": "Ghana Cedi"
  }
}